graftm/__init__.py
graftm/archive.py
graftm/classify.py
graftm/clusterer.py
graftm/create.py
graftm/db_search_results.py
graftm/decorator.py
graftm/decoy_filter.py
graftm/deduplicator.py
graftm/dendropy_tree_cleaner.py
graftm/diamond.py
graftm/expand_searcher.py
graftm/external_program_suite.py
graftm/getaxnseq.py
graftm/graftm_output_paths.py
graftm/graftm_package.py
graftm/greengenes_taxonomy.py
graftm/hmmsearcher.py
graftm/housekeeping.py
graftm/orfm.py
graftm/pplacer.py
graftm/readHmmTable.py
graftm/reannotator.py
graftm/rerooter.py
graftm/run.py
graftm/search_table.py
graftm/sequence_extractor.py
graftm/sequence_io.py
graftm/sequence_search_results.py
graftm/sequence_searcher.py
graftm/summarise.py
graftm/taxonomy_cleaner.py
graftm/taxonomy_extractor.py
graftm/timeit.py
graftm/tree_decorator.py
graftm/unpack_sequences.py
graftm/update.py
graftm/version.py
graftm-0.15.1.data/data/share/18S.hmm
graftm-0.15.1.data/scripts/graftM
graftm-0.15.1.dist-info/LICENCE.txt
graftm-0.15.1.dist-info/METADATA
graftm-0.15.1.dist-info/WHEEL
graftm-0.15.1.dist-info/top_level.txt
graftm-0.15.1.dist-info/RECORD
