Metadata-Version: 2.1
Name: graftm
Version: 0.15.1
Summary: GraftM is a pipeline used for identifying and classifying marker gene reads from metagenomic datasets
Home-page: http://geronimp.github.io/graftM
Author: Joel Boyd, Ben Woodcroft
License: GPL3+
License-File: LICENCE.txt
Requires-Dist: biopython >=1.64
Requires-Dist: biom-format >=2.1.4
Requires-Dist: extern >=0.0.4
Requires-Dist: taxtastic >=0.5.4
Requires-Dist: bird-tool-utils >=0.2.17
Requires-Dist: DendroPy >=4.1.0
Requires-Dist: pyyaml
Requires-Dist: fastalite
Requires-Dist: jinja2
